README.rst
setup.cfg
setup.py
bittivahti/__init__.py
bittivahti/bittivahti.py
bittivahti/cli.py
bittivahti/terminal.py
bittivahti/utils.py
bittivahti.egg-info/PKG-INFO
bittivahti.egg-info/SOURCES.txt
bittivahti.egg-info/dependency_links.txt
bittivahti.egg-info/entry_points.txt
bittivahti.egg-info/not-zip-safe
bittivahti.egg-info/requires.txt
bittivahti.egg-info/top_level.txt