Metadata-Version: 1.1
Name: bittivahti
Version: 0.9.3
Summary: Bittivahti bandwidth monitor for Linux
Home-page: https://github.com/joneskoo/bittivahti
Author: Joonas Kuorilehto
Author-email: joneskoo@kapsi.fi
License: MIT
Platform: UNKNOWN
Classifier: Development Status :: 3 - Alpha
Classifier: Environment :: Console
Classifier: Intended Audience :: System Administrators
Classifier: License :: OSI Approved :: MIT License
Classifier: Operating System :: POSIX :: Linux
Classifier: Programming Language :: Python
Classifier: Programming Language :: Python :: 2
Classifier: Programming Language :: Python :: 2.7
Classifier: Programming Language :: Python :: 3
Classifier: Programming Language :: Python :: 3.4
Classifier: Topic :: Internet
Classifier: Topic :: System :: Networking
Classifier: Topic :: Utilities
